<annotation>
  <filename>Misc_398</filename>
  <size>
    <width>281</width>
    <height>284</height>
    <depth>1</depth>
  </size>
  <object>
    <name>Target</name>
    <bndbox>
      <xmin>55</xmin>
      <ymin>64</ymin>
      <xmax>58</xmax>
      <ymax>68</ymax>
    </bndbox>
  </object>
  <object>
    <name>Target</name>
    <bndbox>
      <xmin>44</xmin>
      <ymin>65</ymin>
      <xmax>48</xmax>
      <ymax>70</ymax>
    </bndbox>
  </object>
  <object>
    <name>Target</name>
    <bndbox>
      <xmin>50</xmin>
      <ymin>65</ymin>
      <xmax>53</xmax>
      <ymax>68</ymax>
    </bndbox>
  </object>
  <object>
    <name>Target</name>
    <bndbox>
      <xmin>49</xmin>
      <ymin>69</ymin>
      <xmax>53</xmax>
      <ymax>73</ymax>
    </bndbox>
  </object>
  <object>
    <name>Target</name>
    <bndbox>
      <xmin>45</xmin>
      <ymin>71</ymin>
      <xmax>48</xmax>
      <ymax>76</ymax>
    </bndbox>
  </object>
  <object>
    <name>Target</name>
    <bndbox>
      <xmin>55</xmin>
      <ymin>71</ymin>
      <xmax>58</xmax>
      <ymax>74</ymax>
    </bndbox>
  </object>
  <object>
    <name>Target</name>
    <bndbox>
      <xmin>50</xmin>
      <ymin>76</ymin>
      <xmax>53</xmax>
      <ymax>80</ymax>
    </bndbox>
  </object>
  <object>
    <name>Target</name>
    <bndbox>
      <xmin>55</xmin>
      <ymin>76</ymin>
      <xmax>58</xmax>
      <ymax>79</ymax>
    </bndbox>
  </object>
  <object>
    <name>Target</name>
    <bndbox>
      <xmin>44</xmin>
      <ymin>78</ymin>
      <xmax>47</xmax>
      <ymax>81</ymax>
    </bndbox>
  </object>
  <object>
    <name>Target</name>
    <bndbox>
      <xmin>69</xmin>
      <ymin>111</ymin>
      <xmax>73</xmax>
      <ymax>115</ymax>
    </bndbox>
  </object>
  <object>
    <name>Target</name>
    <bndbox>
      <xmin>75</xmin>
      <ymin>112</ymin>
      <xmax>78</xmax>
      <ymax>116</ymax>
    </bndbox>
  </object>
  <object>
    <name>Target</name>
    <bndbox>
      <xmin>63</xmin>
      <ymin>116</ymin>
      <xmax>67</xmax>
      <ymax>120</ymax>
    </bndbox>
  </object>
  <object>
    <name>Target</name>
    <bndbox>
      <xmin>70</xmin>
      <ymin>117</ymin>
      <xmax>75</xmax>
      <ymax>121</ymax>
    </bndbox>
  </object>
  <object>
    <name>Target</name>
    <bndbox>
      <xmin>62</xmin>
      <ymin>122</ymin>
      <xmax>65</xmax>
      <ymax>125</ymax>
    </bndbox>
  </object>
  <object>
    <name>Target</name>
    <bndbox>
      <xmin>74</xmin>
      <ymin>122</ymin>
      <xmax>78</xmax>
      <ymax>126</ymax>
    </bndbox>
  </object>
  <object>
    <name>Target</name>
    <bndbox>
      <xmin>67</xmin>
      <ymin>123</ymin>
      <xmax>71</xmax>
      <ymax>127</ymax>
    </bndbox>
  </object>
  <object>
    <name>Target</name>
    <bndbox>
      <xmin>31</xmin>
      <ymin>204</ymin>
      <xmax>35</xmax>
      <ymax>207</ymax>
    </bndbox>
  </object>
  <object>
    <name>Target</name>
    <bndbox>
      <xmin>38</xmin>
      <ymin>205</ymin>
      <xmax>41</xmax>
      <ymax>209</ymax>
    </bndbox>
  </object>
  <object>
    <name>Target</name>
    <bndbox>
      <xmin>42</xmin>
      <ymin>207</ymin>
      <xmax>46</xmax>
      <ymax>211</ymax>
    </bndbox>
  </object>
  <object>
    <name>Target</name>
    <bndbox>
      <xmin>36</xmin>
      <ymin>212</ymin>
      <xmax>39</xmax>
      <ymax>215</ymax>
    </bndbox>
  </object>
  <object>
    <name>Target</name>
    <bndbox>
      <xmin>42</xmin>
      <ymin>216</ymin>
      <xmax>47</xmax>
      <ymax>219</ymax>
    </bndbox>
  </object>
  <object>
    <name>Target</name>
    <bndbox>
      <xmin>36</xmin>
      <ymin>217</ymin>
      <xmax>39</xmax>
      <ymax>220</ymax>
    </bndbox>
  </object>
  <object>
    <name>Target</name>
    <bndbox>
      <xmin>61</xmin>
      <ymin>271</ymin>
      <xmax>69</xmax>
      <ymax>280</ymax>
    </bndbox>
  </object>
</annotation>
